project/m2/rtl/compute_core.sv
/*
 * compute_core.sv  —  Echo detection compute core
 *
 * Ports:
 *   clk        in    1         clock (single domain)
 *   rst        in    1         synchronous active-high reset
 *   valid_in   in    1         input sample pair is valid this cycle
 *   ref_in     in   DW         far-end reference sample (signed INT16)
 *   mic_in     in   DW         near-end mic sample (signed INT16)
 *   threshold  in   ACCW       echo threshold in accumulated cross-correlation units
 *   echo_det   out   1         1 = echo detected (acc_cross >= threshold)
 *   valid_out  out   1         output valid; asserted one cycle after window fills
 *
 * Algorithm: unnormalized cross-correlation Σref[i]*mic[i] vs threshold.
 *   Full normalization (÷ sqrt(ref_energy * mic_energy)) deferred; documented in precision.md.
 * Precision: INT16 samples, 40-bit signed accumulators (32-bit product + 8 overhead bits).
 * Clock domain: single. Reset: synchronous, active-high.
 * Latency: outputs valid N+1 valid_in cycles after reset (window fill).
 */
module compute_core #(
    parameter int N    = 128,
    parameter int DW   = 16,
    parameter int ACCW = 40    // DW*2 + ceil(log2(N)) + 1 = 32+7+1
) (
    input  logic                    clk,
    input  logic                    rst,
    input  logic                    valid_in,
    input  logic signed [DW-1:0]   ref_in,
    input  logic signed [DW-1:0]   mic_in,
    input  logic signed [ACCW-1:0] threshold,
    output logic                    echo_det,
    output logic                    valid_out
);

    localparam int CNTW = $clog2(N) + 1;  // 8 bits for N=128

    logic signed [DW-1:0]   ref_buf [0:N-1];
    logic signed [DW-1:0]   mic_buf [0:N-1];
    logic [CNTW-1:0]        win_cnt;

    // window_full goes high combinationally once win_cnt reaches N
    logic window_full;
    assign window_full = (win_cnt == CNTW'(N));

    // Sign-extend buffers to ACCW bits (combinational, synthesizes as wires)
    logic signed [ACCW-1:0] ref_e [0:N-1];
    logic signed [ACCW-1:0] mic_e [0:N-1];
    genvar g;
    generate
        for (g = 0; g < N; g++) begin : sign_ext
            assign ref_e[g] = ACCW'(ref_buf[g]);  // signed assignment sign-extends
            assign mic_e[g] = ACCW'(mic_buf[g]);
        end
    endgenerate

    // Parallel MAC tree: N multipliers evaluated combinationally each cycle
    logic signed [ACCW-1:0] acc_cross;

    always_comb begin : mac_tree
        acc_cross = '0;
        for (int i = 0; i < N; i++)
            acc_cross = acc_cross + ref_e[i] * mic_e[i];  // 40x40 -> 40-bit (lower bits)
    end

    always_ff @(posedge clk) begin
        if (rst) begin
            for (int i = 0; i < N; i++) begin
                ref_buf[i] <= '0;
                mic_buf[i] <= '0;
            end
            win_cnt   <= '0;
            echo_det  <= 1'b0;
            valid_out <= 1'b0;
        end else if (valid_in) begin
            // Shift new sample into buffer front
            ref_buf[0] <= ref_in;
            mic_buf[0] <= mic_in;
            for (int i = 1; i < N; i++) begin
                ref_buf[i] <= ref_buf[i-1];
                mic_buf[i] <= mic_buf[i-1];
            end
            if (!window_full)
                win_cnt <= win_cnt + 1'b1;
            // Register outputs; acc_cross is computed from pre-shift buffer
            echo_det  <= window_full & (acc_cross >= threshold);
            valid_out <= window_full;
        end else begin
            valid_out <= 1'b0;
        end
    end

endmodule

project/m2/tb/tb_compute_core.sv
`timescale 1ns/1ps

// tb_compute_core.sv  —  Testbench for compute_core
//
// Test 1 (echo present): ref[i]=1, mic[i]=1 for N=128 samples
//   acc_cross = 128, threshold = 64  =>  echo_det=1, valid_out=1  expected PASS
//
// Test 2 (no echo): ref[i]=1, mic[i]=-1 for N=128 samples
//   acc_cross = -128, threshold = 64  =>  echo_det=0, valid_out=1  expected PASS
//
// Reference values computed independently (Python: sum(1*1 for _ in range(128)) = 128).

module tb_compute_core;

    parameter int N    = 128;
    parameter int DW   = 16;
    parameter int ACCW = 40;

    logic                    clk, rst, valid_in;
    logic signed [DW-1:0]   ref_in, mic_in;
    logic signed [ACCW-1:0] threshold;
    logic                    echo_det, valid_out;

    compute_core #(.N(N), .DW(DW), .ACCW(ACCW)) dut (
        .clk(clk), .rst(rst), .valid_in(valid_in),
        .ref_in(ref_in), .mic_in(mic_in),
        .threshold(threshold),
        .echo_det(echo_det), .valid_out(valid_out)
    );

    // 10 ns clock
    initial clk = 0;
    always #5 clk = ~clk;

    // Waveform dump
    initial begin
        $dumpfile("project/m2/sim/compute_core.vcd");
        $dumpvars(0, tb_compute_core);
    end

    integer pass_cnt, fail_cnt;

    task automatic reset_dut;
        rst = 1; valid_in = 0; ref_in = 0; mic_in = 0;
        threshold = 40'sd64;
        repeat(3) @(posedge clk);
        @(negedge clk); rst = 0;
    endtask

    // Send N+1 samples so window fills; task ends at the posedge where outputs are valid
    // Caller must read outputs immediately after return, then clear valid_in
    task automatic send_samples(input logic signed [DW-1:0] rval, mval);
        integer k;
        for (k = 0; k <= N; k++) begin
            @(negedge clk);
            valid_in = 1;
            ref_in   = rval;
            mic_in   = mval;
        end
        @(posedge clk); #1;  // outputs registered here (window_full=1, valid_in=1)
    endtask

    initial begin
        pass_cnt = 0; fail_cnt = 0;

        // ---- Test 1: perfect echo (ref=1, mic=1) ----
        reset_dut();
        send_samples(16'sd1, 16'sd1);
        // Expected: acc_cross = 128 >= threshold=64  =>  echo_det=1, valid_out=1
        if (valid_out === 1'b1 && echo_det === 1'b1) begin
            $display("PASS  test1: echo_det=1 valid_out=1 (acc_cross=128 >= 64)");
            pass_cnt++;
        end else begin
            $display("FAIL  test1: echo_det=%0b valid_out=%0b (expected 1,1)", echo_det, valid_out);
            fail_cnt++;
        end
        @(negedge clk); valid_in = 0;

        // ---- Test 2: anti-correlated (ref=1, mic=-1) ----
        reset_dut();
        send_samples(16'sd1, -16'sd1);
        // Expected: acc_cross = -128 < threshold=64  =>  echo_det=0, valid_out=1
        if (valid_out === 1'b1 && echo_det === 1'b0) begin
            $display("PASS  test2: echo_det=0 valid_out=1 (acc_cross=-128 < 64)");
            pass_cnt++;
        end else begin
            $display("FAIL  test2: echo_det=%0b valid_out=%0b (expected 0,1)", echo_det, valid_out);
            fail_cnt++;
        end
        @(negedge clk); valid_in = 0;

        // ---- Summary ----
        if (fail_cnt == 0)
            $display("PASS  compute_core: %0d/2 tests passed", pass_cnt);
        else
            $display("FAIL  compute_core: %0d test(s) failed", fail_cnt);

        $finish;
    end

endmodule

project/m2/sim/compute_core.vcd
$date
	Fri May  1 16:05:15 2026
$end
$version
	Icarus Verilog
$end
$timescale
	1ps
$end
$scope module tb_compute_core $end
$var wire 1 ! valid_out $end
$var wire 1 " echo_det $end
$var parameter 32 # ACCW $end
$var parameter 32 $ DW $end
$var parameter 32 % N $end
$var reg 1 & clk $end
$var reg 16 ' mic_in [15:0] $end
$var reg 16 ( ref_in [15:0] $end
$var reg 1 ) rst $end
$var reg 40 * threshold [39:0] $end
$var reg 1 + valid_in $end
$var integer 32 , fail_cnt [31:0] $end
$var integer 32 - pass_cnt [31:0] $end
$scope module dut $end
$var wire 1 & clk $end
$var wire 16 . mic_in [15:0] $end
$var wire 16 / ref_in [15:0] $end
$var wire 1 ) rst $end
$var wire 40 0 threshold [39:0] $end
$var wire 1 + valid_in $end
$var wire 1 1 window_full $end
$var parameter 32 2 ACCW $end
$var parameter 32 3 CNTW $end
$var parameter 32 4 DW $end
$var parameter 32 5 N $end
$var reg 40 6 acc_cross [39:0] $end
$var reg 1 " echo_det $end
$var reg 1 ! valid_out $end
$var reg 8 7 win_cnt [7:0] $end
$scope begin sign_ext[0] $end
$var parameter 2 8 g $end
$upscope $end
$scope begin sign_ext[1] $end
$var parameter 2 9 g $end
$upscope $end
$scope begin sign_ext[2] $end
$var parameter 3 : g $end
$upscope $end
$scope begin sign_ext[3] $end
$var parameter 3 ; g $end
$upscope $end
$scope begin sign_ext[4] $end
$var parameter 4 < g $end
$upscope $end
$scope begin sign_ext[5] $end
$var parameter 4 = g $end
$upscope $end
$scope begin sign_ext[6] $end
$var parameter 4 > g $end
$upscope $end
$scope begin sign_ext[7] $end
$var parameter 4 ? g $end
$upscope $end
$scope begin sign_ext[8] $end
$var parameter 5 @ g $end
$upscope $end
$scope begin sign_ext[9] $end
$var parameter 5 A g $end
$upscope $end
$scope begin sign_ext[10] $end
$var parameter 5 B g $end
$upscope $end
$scope begin sign_ext[11] $end
$var parameter 5 C g $end
$upscope $end
$scope begin sign_ext[12] $end
$var parameter 5 D g $end
$upscope $end
$scope begin sign_ext[13] $end
$var parameter 5 E g $end
$upscope $end
$scope begin sign_ext[14] $end
$var parameter 5 F g $end
$upscope $end
$scope begin sign_ext[15] $end
$var parameter 5 G g $end
$upscope $end
$scope begin sign_ext[16] $end
$var parameter 6 H g $end
$upscope $end
$scope begin sign_ext[17] $end
$var parameter 6 I g $end
$upscope $end
$scope begin sign_ext[18] $end
$var parameter 6 J g $end
$upscope $end
$scope begin sign_ext[19] $end
$var parameter 6 K g $end
$upscope $end
$scope begin sign_ext[20] $end
$var parameter 6 L g $end
$upscope $end
$scope begin sign_ext[21] $end
$var parameter 6 M g $end
$upscope $end
$scope begin sign_ext[22] $end
$var parameter 6 N g $end
$upscope $end
$scope begin sign_ext[23] $end
$var parameter 6 O g $end
$upscope $end
$scope begin sign_ext[24] $end
$var parameter 6 P g $end
$upscope $end
$scope begin sign_ext[25] $end
$var parameter 6 Q g $end
$upscope $end
$scope begin sign_ext[26] $end
$var parameter 6 R g $end
$upscope $end
$scope begin sign_ext[27] $end
$var parameter 6 S g $end
$upscope $end
$scope begin sign_ext[28] $end
$var parameter 6 T g $end
$upscope $end
$scope begin sign_ext[29] $end
$var parameter 6 U g $end
$upscope $end
$scope begin sign_ext[30] $end
$var parameter 6 V g $end
$upscope $end
$scope begin sign_ext[31] $end
$var parameter 6 W g $end
$upscope $end
$scope begin sign_ext[32] $end
$var parameter 7 X g $end
$upscope $end
$scope begin sign_ext[33] $end
$var parameter 7 Y g $end
$upscope $end
$scope begin sign_ext[34] $end
$var parameter 7 Z g $end
$upscope $end
$scope begin sign_ext[35] $end
$var parameter 7 [ g $end
$upscope $end
$scope begin sign_ext[36] $end
$var parameter 7 \ g $end
$upscope $end
$scope begin sign_ext[37] $end
$var parameter 7 ] g $end
$upscope $end
$scope begin sign_ext[38] $end
$var parameter 7 ^ g $end
$upscope $end
$scope begin sign_ext[39] $end
$var parameter 7 _ g $end
$upscope $end
$scope begin sign_ext[40] $end
$var parameter 7 ` g $end
$upscope $end
$scope begin sign_ext[41] $end
$var parameter 7 a g $end
$upscope $end
$scope begin sign_ext[42] $end
$var parameter 7 b g $end
$upscope $end
$scope begin sign_ext[43] $end
$var parameter 7 c g $end
$upscope $end
$scope begin sign_ext[44] $end
$var parameter 7 d g $end
$upscope $end
$scope begin sign_ext[45] $end
$var parameter 7 e g $end
$upscope $end
$scope begin sign_ext[46] $end
$var parameter 7 f g $end
$upscope $end
$scope begin sign_ext[47] $end
$var parameter 7 g g $end
$upscope $end
$scope begin sign_ext[48] $end
$var parameter 7 h g $end
$upscope $end
$scope begin sign_ext[49] $end
$var parameter 7 i g $end
$upscope $end
$scope begin sign_ext[50] $end
$var parameter 7 j g $end
$upscope $end
$scope begin sign_ext[51] $end
$var parameter 7 k g $end
$upscope $end
$scope begin sign_ext[52] $end
$var parameter 7 l g $end
$upscope $end
$scope begin sign_ext[53] $end
$var parameter 7 m g $end
$upscope $end
$scope begin sign_ext[54] $end
$var parameter 7 n g $end
$upscope $end
$scope begin sign_ext[55] $end
$var parameter 7 o g $end
$upscope $end
$scope begin sign_ext[56] $end
$var parameter 7 p g $end
$upscope $end
$scope begin sign_ext[57] $end
$var parameter 7 q g $end
$upscope $end
$scope begin sign_ext[58] $end
$var parameter 7 r g $end
$upscope $end
$scope begin sign_ext[59] $end
$var parameter 7 s g $end
$upscope $end
$scope begin sign_ext[60] $end
$var parameter 7 t g $end
$upscope $end
$scope begin sign_ext[61] $end
$var parameter 7 u g $end
$upscope $end
$scope begin sign_ext[62] $end
$var parameter 7 v g $end
$upscope $end
$scope begin sign_ext[63] $end
$var parameter 7 w g $end
$upscope $end
$scope begin sign_ext[64] $end
$var parameter 8 x g $end
$upscope $end
$scope begin sign_ext[65] $end
$var parameter 8 y g $end
$upscope $end
$scope begin sign_ext[66] $end
$var parameter 8 z g $end
$upscope $end
$scope begin sign_ext[67] $end
$var parameter 8 { g $end
$upscope $end
$scope begin sign_ext[68] $end
$var parameter 8 | g $end
$upscope $end
$scope begin sign_ext[69] $end
$var parameter 8 } g $end
$upscope $end
$scope begin sign_ext[70] $end
$var parameter 8 ~ g $end
$upscope $end
$scope begin sign_ext[71] $end
$var parameter 8 !" g $end
$upscope $end
$scope begin sign_ext[72] $end
$var parameter 8 "" g $end
$upscope $end
$scope begin sign_ext[73] $end
$var parameter 8 #" g $end
$upscope $end
$scope begin sign_ext[74] $end
$var parameter 8 $" g $end
$upscope $end
$scope begin sign_ext[75] $end
$var parameter 8 %" g $end
$upscope $end
$scope begin sign_ext[76] $end
$var parameter 8 &" g $end
$upscope $end
$scope begin sign_ext[77] $end
$var parameter 8 '" g $end
$upscope $end
$scope begin sign_ext[78] $end
$var parameter 8 (" g $end
$upscope $end
$scope begin sign_ext[79] $end
$var parameter 8 )" g $end
$upscope $end
$scope begin sign_ext[80] $end
$var parameter 8 *" g $end
$upscope $end
$scope begin sign_ext[81] $end
$var parameter 8 +" g $end
$upscope $end
$scope begin sign_ext[82] $end
$var parameter 8 ," g $end
$upscope $end
$scope begin sign_ext[83] $end
$var parameter 8 -" g $end
$upscope $end
$scope begin sign_ext[84] $end
$var parameter 8 ." g $end
$upscope $end
$scope begin sign_ext[85] $end
$var parameter 8 /" g $end
$upscope $end
$scope begin sign_ext[86] $end
$var parameter 8 0" g $end
$upscope $end
$scope begin sign_ext[87] $end
$var parameter 8 1" g $end
$upscope $end
$scope begin sign_ext[88] $end
$var parameter 8 2" g $end
$upscope $end
$scope begin sign_ext[89] $end
$var parameter 8 3" g $end
$upscope $end
$scope begin sign_ext[90] $end
$var parameter 8 4" g $end
$upscope $end
$scope begin sign_ext[91] $end
$var parameter 8 5" g $end
$upscope $end
$scope begin sign_ext[92] $end
$var parameter 8 6" g $end
$upscope $end
$scope begin sign_ext[93] $end
$var parameter 8 7" g $end
$upscope $end
$scope begin sign_ext[94] $end
$var parameter 8 8" g $end
$upscope $end
$scope begin sign_ext[95] $end
$var parameter 8 9" g $end
$upscope $end
$scope begin sign_ext[96] $end
$var parameter 8 :" g $end
$upscope $end
$scope begin sign_ext[97] $end
$var parameter 8 ;" g $end
$upscope $end
$scope begin sign_ext[98] $end
$var parameter 8 <" g $end
$upscope $end
$scope begin sign_ext[99] $end
$var parameter 8 =" g $end
$upscope $end
$scope begin sign_ext[100] $end
$var parameter 8 >" g $end
$upscope $end
$scope begin sign_ext[101] $end
$var parameter 8 ?" g $end
$upscope $end
$scope begin sign_ext[102] $end
$var parameter 8 @" g $end
$upscope $end
$scope begin sign_ext[103] $end
$var parameter 8 A" g $end
$upscope $end
$scope begin sign_ext[104] $end
$var parameter 8 B" g $end
$upscope $end
$scope begin sign_ext[105] $end
$var parameter 8 C" g $end
$upscope $end
$scope begin sign_ext[106] $end
$var parameter 8 D" g $end
$upscope $end
$scope begin sign_ext[107] $end
$var parameter 8 E" g $end
$upscope $end
$scope begin sign_ext[108] $end
$var parameter 8 F" g $end
$upscope $end
$scope begin sign_ext[109] $end
$var parameter 8 G" g $end
$upscope $end
$scope begin sign_ext[110] $end
$var parameter 8 H" g $end
$upscope $end
$scope begin sign_ext[111] $end
$var parameter 8 I" g $end
$upscope $end
$scope begin sign_ext[112] $end
$var parameter 8 J" g $end
$upscope $end
$scope begin sign_ext[113] $end
$var parameter 8 K" g $end
$upscope $end
$scope begin sign_ext[114] $end
$var parameter 8 L" g $end
$upscope $end
$scope begin sign_ext[115] $end
$var parameter 8 M" g $end
$upscope $end
$scope begin sign_ext[116] $end
$var parameter 8 N" g $end
$upscope $end
$scope begin sign_ext[117] $end
$var parameter 8 O" g $end
$upscope $end
$scope begin sign_ext[118] $end
$var parameter 8 P" g $end
$upscope $end
$scope begin sign_ext[119] $end
$var parameter 8 Q" g $end
$upscope $end
$scope begin sign_ext[120] $end
$var parameter 8 R" g $end
$upscope $end
$scope begin sign_ext[121] $end
$var parameter 8 S" g $end
$upscope $end
$scope begin sign_ext[122] $end
$var parameter 8 T" g $end
$upscope $end
$scope begin sign_ext[123] $end
$var parameter 8 U" g $end
$upscope $end
$scope begin sign_ext[124] $end
$var parameter 8 V" g $end
$upscope $end
$scope begin sign_ext[125] $end
$var parameter 8 W" g $end
$upscope $end
$scope begin sign_ext[126] $end
$var parameter 8 X" g $end
$upscope $end
$scope begin sign_ext[127] $end
$var parameter 8 Y" g $end
$upscope $end
$scope begin $ivl_for_loop1 $end
$var integer 32 Z" i [31:0] $end
$upscope $end
$scope begin $ivl_for_loop2 $end
$var integer 32 [" i [31:0] $end
$upscope $end
$scope begin mac_tree $end
$scope begin $ivl_for_loop0 $end
$var integer 32 \" i [31:0] $end
$upscope $end
$upscope $end
$upscope $end
$scope task reset_dut $end
$upscope $end
$scope task send_samples $end
$upscope $end
$upscope $end
$enddefinitions $end
$comment Show the parameter values. $end
$dumpall
b1111111 Y"
b1111110 X"
b1111101 W"
b1111100 V"
b1111011 U"
b1111010 T"
b1111001 S"
b1111000 R"
b1110111 Q"
b1110110 P"
b1110101 O"
b1110100 N"
b1110011 M"
b1110010 L"
b1110001 K"
b1110000 J"
b1101111 I"
b1101110 H"
b1101101 G"
b1101100 F"
b1101011 E"
b1101010 D"
b1101001 C"
b1101000 B"
b1100111 A"
b1100110 @"
b1100101 ?"
b1100100 >"
b1100011 ="
b1100010 <"
b1100001 ;"
b1100000 :"
b1011111 9"
b1011110 8"
b1011101 7"
b1011100 6"
b1011011 5"
b1011010 4"
b1011001 3"
b1011000 2"
b1010111 1"
b1010110 0"
b1010101 /"
b1010100 ."
b1010011 -"
b1010010 ,"
b1010001 +"
b1010000 *"
b1001111 )"
b1001110 ("
b1001101 '"
b1001100 &"
b1001011 %"
b1001010 $"
b1001001 #"
b1001000 ""
b1000111 !"
b1000110 ~
b1000101 }
b1000100 |
b1000011 {
b1000010 z
b1000001 y
b1000000 x
b111111 w
b111110 v
b111101 u
b111100 t
b111011 s
b111010 r
b111001 q
b111000 p
b110111 o
b110110 n
b110101 m
b110100 l
b110011 k
b110010 j
b110001 i
b110000 h
b101111 g
b101110 f
b101101 e
b101100 d
b101011 c
b101010 b
b101001 a
b101000 `
b100111 _
b100110 ^
b100101 ]
b100100 \
b100011 [
b100010 Z
b100001 Y
b100000 X
b11111 W
b11110 V
b11101 U
b11100 T
b11011 S
b11010 R
b11001 Q
b11000 P
b10111 O
b10110 N
b10101 M
b10100 L
b10011 K
b10010 J
b10001 I
b10000 H
b1111 G
b1110 F
b1101 E
b1100 D
b1011 C
b1010 B
b1001 A
b1000 @
b111 ?
b110 >
b101 =
b100 <
b11 ;
b10 :
b1 9
b0 8
b10000000 5
b10000 4
b1000 3
b101000 2
b10000000 %
b10000 $
b101000 #
$end
#0
$dumpvars
b10000000 \"
b0 ["
b0 Z"
bx 7
bx 6
x1
b1000000 0
b0 /
b0 .
b0 -
b0 ,
0+
b1000000 *
1)
b0 (
b0 '
0&
x"
x!
$end
#5000
b10000000 \"
b0 6
0!
0"
01
b0 7
b10000000 Z"
1&
#10000
0&
#15000
b10000000 Z"
1&
#20000
0&
#25000
b10000000 Z"
1&
#30000
0)
0&
#35000
1&
#40000
b1 '
b1 .
b1 (
b1 /
1+
0&
#45000
b1 6
b10000000 \"
b1 7
b10000000 ["
1&
#50000
0&
#55000
b10000000 \"
b10 6
b10 7
b10000000 ["
1&
#60000
0&
#65000
b10000000 \"
b11 6
b11 7
b10000000 ["
1&
#70000
0&
#75000
b10000000 \"
b100 6
b100 7
b10000000 ["
1&
#80000
0&
#85000
b10000000 \"
b101 6
b101 7
b10000000 ["
1&
#90000
0&
#95000
b10000000 \"
b110 6
b110 7
b10000000 ["
1&
#100000
0&
#105000
b10000000 \"
b111 6
b111 7
b10000000 ["
1&
#110000
0&
#115000
b10000000 \"
b1000 6
b1000 7
b10000000 ["
1&
#120000
0&
#125000
b10000000 \"
b1001 6
b1001 7
b10000000 ["
1&
#130000
0&
#135000
b10000000 \"
b1010 6
b1010 7
b10000000 ["
1&
#140000
0&
#145000
b10000000 \"
b1011 6
b1011 7
b10000000 ["
1&
#150000
0&
#155000
b10000000 \"
b1100 6
b1100 7
b10000000 ["
1&
#160000
0&
#165000
b10000000 \"
b1101 6
b1101 7
b10000000 ["
1&
#170000
0&
#175000
b10000000 \"
b1110 6
b1110 7
b10000000 ["
1&
#180000
0&
#185000
b10000000 \"
b1111 6
b1111 7
b10000000 ["
1&
#190000
0&
#195000
b10000000 \"
b10000 6
b10000 7
b10000000 ["
1&
#200000
0&
#205000
b10000000 \"
b10001 6
b10001 7
b10000000 ["
1&
#210000
0&
#215000
b10000000 \"
b10010 6
b10010 7
b10000000 ["
1&
#220000
0&
#225000
b10000000 \"
b10011 6
b10011 7
b10000000 ["
1&
#230000
0&
#235000
b10000000 \"
b10100 6
b10100 7
b10000000 ["
1&
#240000
0&
#245000
b10000000 \"
b10101 6
b10101 7
b10000000 ["
1&
#250000
0&
#255000
b10000000 \"
b10110 6
b10110 7
b10000000 ["
1&
#260000
0&
#265000
b10000000 \"
b10111 6
b10111 7
b10000000 ["
1&
#270000
0&
#275000
b10000000 \"
b11000 6
b11000 7
b10000000 ["
1&
#280000
0&
#285000
b10000000 \"
b11001 6
b11001 7
b10000000 ["
1&
#290000
0&
#295000
b10000000 \"
b11010 6
b11010 7
b10000000 ["
1&
#300000
0&
#305000
b10000000 \"
b11011 6
b11011 7
b10000000 ["
1&
#310000
0&
#315000
b10000000 \"
b11100 6
b11100 7
b10000000 ["
1&
#320000
0&
#325000
b10000000 \"
b11101 6
b11101 7
b10000000 ["
1&
#330000
0&
#335000
b10000000 \"
b11110 6
b11110 7
b10000000 ["
1&
#340000
0&
#345000
b10000000 \"
b11111 6
b11111 7
b10000000 ["
1&
#350000
0&
#355000
b10000000 \"
b100000 6
b100000 7
b10000000 ["
1&
#360000
0&
#365000
b10000000 \"
b100001 6
b100001 7
b10000000 ["
1&
#370000
0&
#375000
b10000000 \"
b100010 6
b100010 7
b10000000 ["
1&
#380000
0&
#385000
b10000000 \"
b100011 6
b100011 7
b10000000 ["
1&
#390000
0&
#395000
b10000000 \"
b100100 6
b100100 7
b10000000 ["
1&
#400000
0&
#405000
b10000000 \"
b100101 6
b100101 7
b10000000 ["
1&
#410000
0&
#415000
b10000000 \"
b100110 6
b100110 7
b10000000 ["
1&
#420000
0&
#425000
b10000000 \"
b100111 6
b100111 7
b10000000 ["
1&
#430000
0&
#435000
b10000000 \"
b101000 6
b101000 7
b10000000 ["
1&
#440000
0&
#445000
b10000000 \"
b101001 6
b101001 7
b10000000 ["
1&
#450000
0&
#455000
b10000000 \"
b101010 6
b101010 7
b10000000 ["
1&
#460000
0&
#465000
b10000000 \"
b101011 6
b101011 7
b10000000 ["
1&
#470000
0&
#475000
b10000000 \"
b101100 6
b101100 7
b10000000 ["
1&
#480000
0&
#485000
b10000000 \"
b101101 6
b101101 7
b10000000 ["
1&
#490000
0&
#495000
b10000000 \"
b101110 6
b101110 7
b10000000 ["
1&
#500000
0&
#505000
b10000000 \"
b101111 6
b101111 7
b10000000 ["
1&
#510000
0&
#515000
b10000000 \"
b110000 6
b110000 7
b10000000 ["
1&
#520000
0&
#525000
b10000000 \"
b110001 6
b110001 7
b10000000 ["
1&
#530000
0&
#535000
b10000000 \"
b110010 6
b110010 7
b10000000 ["
1&
#540000
0&
#545000
b10000000 \"
b110011 6
b110011 7
b10000000 ["
1&
#550000
0&
#555000
b10000000 \"
b110100 6
b110100 7
b10000000 ["
1&
#560000
0&
#565000
b10000000 \"
b110101 6
b110101 7
b10000000 ["
1&
#570000
0&
#575000
b10000000 \"
b110110 6
b110110 7
b10000000 ["
1&
#580000
0&
#585000
b10000000 \"
b110111 6
b110111 7
b10000000 ["
1&
#590000
0&
#595000
b10000000 \"
b111000 6
b111000 7
b10000000 ["
1&
#600000
0&
#605000
b10000000 \"
b111001 6
b111001 7
b10000000 ["
1&
#610000
0&
#615000
b10000000 \"
b111010 6
b111010 7
b10000000 ["
1&
#620000
0&
#625000
b10000000 \"
b111011 6
b111011 7
b10000000 ["
1&
#630000
0&
#635000
b10000000 \"
b111100 6
b111100 7
b10000000 ["
1&
#640000
0&
#645000
b10000000 \"
b111101 6
b111101 7
b10000000 ["
1&
#650000
0&
#655000
b10000000 \"
b111110 6
b111110 7
b10000000 ["
1&
#660000
0&
#665000
b10000000 \"
b111111 6
b111111 7
b10000000 ["
1&
#670000
0&
#675000
b10000000 \"
b1000000 6
b1000000 7
b10000000 ["
1&
#680000
0&
#685000
b10000000 \"
b1000001 6
b1000001 7
b10000000 ["
1&
#690000
0&
#695000
b10000000 \"
b1000010 6
b1000010 7
b10000000 ["
1&
#700000
0&
#705000
b10000000 \"
b1000011 6
b1000011 7
b10000000 ["
1&
#710000
0&
#715000
b10000000 \"
b1000100 6
b1000100 7
b10000000 ["
1&
#720000
0&
#725000
b10000000 \"
b1000101 6
b1000101 7
b10000000 ["
1&
#730000
0&
#735000
b10000000 \"
b1000110 6
b1000110 7
b10000000 ["
1&
#740000
0&
#745000
b10000000 \"
b1000111 6
b1000111 7
b10000000 ["
1&
#750000
0&
#755000
b10000000 \"
b1001000 6
b1001000 7
b10000000 ["
1&
#760000
0&
#765000
b10000000 \"
b1001001 6
b1001001 7
b10000000 ["
1&
#770000
0&
#775000
b10000000 \"
b1001010 6
b1001010 7
b10000000 ["
1&
#780000
0&
#785000
b10000000 \"
b1001011 6
b1001011 7
b10000000 ["
1&
#790000
0&
#795000
b10000000 \"
b1001100 6
b1001100 7
b10000000 ["
1&
#800000
0&
#805000
b10000000 \"
b1001101 6
b1001101 7
b10000000 ["
1&
#810000
0&
#815000
b10000000 \"
b1001110 6
b1001110 7
b10000000 ["
1&
#820000
0&
#825000
b10000000 \"
b1001111 6
b1001111 7
b10000000 ["
1&
#830000
0&
#835000
b10000000 \"
b1010000 6
b1010000 7
b10000000 ["
1&
#840000
0&
#845000
b10000000 \"
b1010001 6
b1010001 7
b10000000 ["
1&
#850000
0&
#855000
b10000000 \"
b1010010 6
b1010010 7
b10000000 ["
1&
#860000
0&
#865000
b10000000 \"
b1010011 6
b1010011 7
b10000000 ["
1&
#870000
0&
#875000
b10000000 \"
b1010100 6
b1010100 7
b10000000 ["
1&
#880000
0&
#885000
b10000000 \"
b1010101 6
b1010101 7
b10000000 ["
1&
#890000
0&
#895000
b10000000 \"
b1010110 6
b1010110 7
b10000000 ["
1&
#900000
0&
#905000
b10000000 \"
b1010111 6
b1010111 7
b10000000 ["
1&
#910000
0&
#915000
b10000000 \"
b1011000 6
b1011000 7
b10000000 ["
1&
#920000
0&
#925000
b10000000 \"
b1011001 6
b1011001 7
b10000000 ["
1&
#930000
0&
#935000
b10000000 \"
b1011010 6
b1011010 7
b10000000 ["
1&
#940000
0&
#945000
b10000000 \"
b1011011 6
b1011011 7
b10000000 ["
1&
#950000
0&
#955000
b10000000 \"
b1011100 6
b1011100 7
b10000000 ["
1&
#960000
0&
#965000
b10000000 \"
b1011101 6
b1011101 7
b10000000 ["
1&
#970000
0&
#975000
b10000000 \"
b1011110 6
b1011110 7
b10000000 ["
1&
#980000
0&
#985000
b10000000 \"
b1011111 6
b1011111 7
b10000000 ["
1&
#990000
0&
#995000
b10000000 \"
b1100000 6
b1100000 7
b10000000 ["
1&
#1000000
0&
#1005000
b10000000 \"
b1100001 6
b1100001 7
b10000000 ["
1&
#1010000
0&
#1015000
b10000000 \"
b1100010 6
b1100010 7
b10000000 ["
1&
#1020000
0&
#1025000
b10000000 \"
b1100011 6
b1100011 7
b10000000 ["
1&
#1030000
0&
#1035000
b10000000 \"
b1100100 6
b1100100 7
b10000000 ["
1&
#1040000
0&
#1045000
b10000000 \"
b1100101 6
b1100101 7
b10000000 ["
1&
#1050000
0&
#1055000
b10000000 \"
b1100110 6
b1100110 7
b10000000 ["
1&
#1060000
0&
#1065000
b10000000 \"
b1100111 6
b1100111 7
b10000000 ["
1&
#1070000
0&
#1075000
b10000000 \"
b1101000 6
b1101000 7
b10000000 ["
1&
#1080000
0&
#1085000
b10000000 \"
b1101001 6
b1101001 7
b10000000 ["
1&
#1090000
0&
#1095000
b10000000 \"
b1101010 6
b1101010 7
b10000000 ["
1&
#1100000
0&
#1105000
b10000000 \"
b1101011 6
b1101011 7
b10000000 ["
1&
#1110000
0&
#1115000
b10000000 \"
b1101100 6
b1101100 7
b10000000 ["
1&
#1120000
0&
#1125000
b10000000 \"
b1101101 6
b1101101 7
b10000000 ["
1&
#1130000
0&
#1135000
b10000000 \"
b1101110 6
b1101110 7
b10000000 ["
1&
#1140000
0&
#1145000
b10000000 \"
b1101111 6
b1101111 7
b10000000 ["
1&
#1150000
0&
#1155000
b10000000 \"
b1110000 6
b1110000 7
b10000000 ["
1&
#1160000
0&
#1165000
b10000000 \"
b1110001 6
b1110001 7
b10000000 ["
1&
#1170000
0&
#1175000
b10000000 \"
b1110010 6
b1110010 7
b10000000 ["
1&
#1180000
0&
#1185000
b10000000 \"
b1110011 6
b1110011 7
b10000000 ["
1&
#1190000
0&
#1195000
b10000000 \"
b1110100 6
b1110100 7
b10000000 ["
1&
#1200000
0&
#1205000
b10000000 \"
b1110101 6
b1110101 7
b10000000 ["
1&
#1210000
0&
#1215000
b10000000 \"
b1110110 6
b1110110 7
b10000000 ["
1&
#1220000
0&
#1225000
b10000000 \"
b1110111 6
b1110111 7
b10000000 ["
1&
#1230000
0&
#1235000
b10000000 \"
b1111000 6
b1111000 7
b10000000 ["
1&
#1240000
0&
#1245000
b10000000 \"
b1111001 6
b1111001 7
b10000000 ["
1&
#1250000
0&
