project/m2/rtl/interface.sv
/*
 * interface.sv  —  AXI4-Stream slave interface for echo detection chiplet
 *
 * Note: 'interface' is a SystemVerilog reserved keyword; module is named axi4s_rx.
 *   File named interface.sv per M2 spec. See project/m2/README.md.
 *
 * Ports:
 *   clk        in    1         clock (single domain)
 *   rst        in    1         synchronous active-high reset
 *   s_tvalid   in    1         AXI4-S: master data valid
 *   s_tready   out   1         AXI4-S: slave ready (always asserted; no back-pressure)
 *   s_tdata    in   32         AXI4-S: [31:16]=ref_sample, [15:0]=mic_sample
 *   ref_out    out  16         decoded far-end reference sample (signed INT16)
 *   mic_out    out  16         decoded near-end mic sample (signed INT16)
 *   valid_out  out   1         decoded pair valid (registered one cycle after TVALID)
 *
 * Protocol: AXI4-Stream (AMBA AXI4-S spec section 2).
 *   TREADY is wired high; transaction occurs on every TVALID cycle.
 *   TDATA packing: upper 16 bits = ref, lower 16 bits = mic.
 *   No TLAST, TKEEP, TSTRB (single-beat, continuous stream).
 * Clock domain: single. Reset: synchronous, active-high.
 */
module axi4s_rx (
    input  logic        clk,
    input  logic        rst,
    // AXI4-Stream slave
    input  logic        s_tvalid,
    output logic        s_tready,
    input  logic [31:0] s_tdata,
    // decoded outputs to compute_core
    output logic signed [15:0] ref_out,
    output logic signed [15:0] mic_out,
    output logic               valid_out
);

    // Always ready: accept every beat; no FIFO or flow control needed at 0.064 MB/s
    assign s_tready = 1'b1;

    always_ff @(posedge clk) begin
        if (rst) begin
            ref_out   <= '0;
            mic_out   <= '0;
            valid_out <= 1'b0;
        end else begin
            valid_out <= s_tvalid;
            if (s_tvalid) begin
                ref_out <= s_tdata[31:16];
                mic_out <= s_tdata[15:0];
            end
        end
    end

endmodule

project/m2/tb/tb_interface.sv
`timescale 1ns/1ps

// tb_interface.sv  —  Testbench for axi4s_rx (interface.sv)
//
// Test 1 (write): TVALID=1, TDATA=32'hABCD_1234 -> ref_out=0xABCD, mic_out=0x1234, valid_out=1
// Test 2 (idle):  TVALID=0                       -> valid_out=0
// Test 3 (back-to-back): two consecutive beats, verify each decoded independently

module tb_interface;

    logic        clk, rst;
    logic        s_tvalid, s_tready;
    logic [31:0] s_tdata;
    logic signed [15:0] ref_out, mic_out;
    logic        valid_out;

    axi4s_rx dut (
        .clk(clk), .rst(rst),
        .s_tvalid(s_tvalid), .s_tready(s_tready), .s_tdata(s_tdata),
        .ref_out(ref_out), .mic_out(mic_out), .valid_out(valid_out)
    );

    initial clk = 0;
    always #5 clk = ~clk;

    initial begin
        $dumpfile("project/m2/sim/interface.vcd");
        $dumpvars(0, tb_interface);
    end

    integer pass_cnt, fail_cnt;

    initial begin
        pass_cnt = 0; fail_cnt = 0;
        rst = 1; s_tvalid = 0; s_tdata = 0;
        repeat(3) @(posedge clk);
        @(negedge clk); rst = 0;

        // ---- Test 1: single write transaction ----
        // Set TVALID and TDATA before the posedge; outputs are registered at posedge
        @(negedge clk);
        s_tvalid = 1; s_tdata = 32'hABCD_1234;
        @(posedge clk); #1;  // outputs registered here
        if (valid_out === 1'b1 && ref_out === 16'hABCD && mic_out === 16'h1234) begin
            $display("PASS  test1: ref_out=0xABCD mic_out=0x1234 valid_out=1");
            pass_cnt++;
        end else begin
            $display("FAIL  test1: ref_out=%h mic_out=%h valid_out=%0b", ref_out, mic_out, valid_out);
            fail_cnt++;
        end

        // ---- Test 2: idle (TVALID=0) ----
        @(negedge clk); s_tvalid = 0;
        @(posedge clk); #1;
        if (valid_out === 1'b0) begin
            $display("PASS  test2: valid_out=0 when TVALID=0");
            pass_cnt++;
        end else begin
            $display("FAIL  test2: valid_out=%0b expected 0", valid_out);
            fail_cnt++;
        end

        // ---- Test 3: back-to-back beats ----
        @(negedge clk); s_tvalid = 1; s_tdata = 32'h0001_0002;
        @(posedge clk); #1;  // beat 1 registered
        if (valid_out === 1'b1 && ref_out === 16'h0001 && mic_out === 16'h0002) begin
            $display("PASS  test3a: beat1 ref=1 mic=2 valid_out=1");
            pass_cnt++;
        end else begin
            $display("FAIL  test3a: ref_out=%h mic_out=%h valid_out=%0b", ref_out, mic_out, valid_out);
            fail_cnt++;
        end
        @(negedge clk); s_tdata = 32'h0003_0004;  // TVALID still 1
        @(posedge clk); #1;  // beat 2 registered
        if (valid_out === 1'b1 && ref_out === 16'h0003 && mic_out === 16'h0004) begin
            $display("PASS  test3b: beat2 ref=3 mic=4 valid_out=1");
            pass_cnt++;
        end else begin
            $display("FAIL  test3b: ref_out=%h mic_out=%h valid_out=%0b", ref_out, mic_out, valid_out);
            fail_cnt++;
        end
        @(negedge clk); s_tvalid = 0;

        // ---- Summary ----
        if (fail_cnt == 0)
            $display("PASS  axi4s_rx: %0d/4 tests passed", pass_cnt);
        else
            $display("FAIL  axi4s_rx: %0d test(s) failed", fail_cnt);

        $finish;
    end

endmodule

project/m2/sim/interface.vcd
$date
	Fri May  1 16:05:15 2026
$end
$version
	Icarus Verilog
$end
$timescale
	1ps
$end
$scope module tb_interface $end
$var wire 1 ! s_tready $end
$var wire 1 " valid_out $end
$var wire 16 # ref_out [15:0] $end
$var wire 16 $ mic_out [15:0] $end
$var reg 1 % clk $end
$var reg 1 & rst $end
$var reg 32 ' s_tdata [31:0] $end
$var reg 1 ( s_tvalid $end
$var integer 32 ) fail_cnt [31:0] $end
$var integer 32 * pass_cnt [31:0] $end
$scope module dut $end
$var wire 1 % clk $end
$var wire 1 & rst $end
$var wire 32 + s_tdata [31:0] $end
$var wire 1 ! s_tready $end
$var wire 1 ( s_tvalid $end
$var reg 16 , mic_out [15:0] $end
$var reg 16 - ref_out [15:0] $end
$var reg 1 " valid_out $end
$upscope $end
$upscope $end
$enddefinitions $end
$comment Show the parameter values. $end
$dumpall
$end
#0
$dumpvars
bx -
bx ,
b0 +
b0 *
b0 )
0(
b0 '
1&
0%
bx $
bx #
x"
1!
$end
#5000
0"
b0 $
b0 ,
b0 #
b0 -
1%
#10000
0%
#15000
1%
#20000
0%
#25000
1%
#30000
0&
0%
#35000
1%
#40000
b10101011110011010001001000110100 '
b10101011110011010001001000110100 +
1(
0%
#45000
b1001000110100 $
b1001000110100 ,
b1010101111001101 #
b1010101111001101 -
1"
1%
#46000
b1 *
#50000
0(
0%
#55000
0"
1%
#56000
b10 *
#60000
b10000000000000010 '
b10000000000000010 +
1(
0%
#65000
b10 $
b10 ,
b1 #
b1 -
1"
1%
#66000
b11 *
#70000
b110000000000000100 '
b110000000000000100 +
0%
#75000
b100 $
b100 ,
b11 #
b11 -
1%
#76000
b100 *
#80000
0(
0%
