codefest/cf04/hdl/mac_correct.v
module mac (
    input  logic              clk,
    input  logic              rst,
    input  logic signed [7:0] a,
    input  logic signed [7:0] b,
    output logic signed [31:0] out
);

    logic signed [15:0] product;
    assign product = a * b;

    always_ff @(posedge clk) begin
        if (rst)
            out <= '0;
        else
            out <= out + {{16{product[15]}}, product};
    end

endmodule

codefest/cf04/hdl/mac_tb.v
`timescale 1ns/1ps
module mac_tb;
    reg              clk, rst;
    reg  signed [7:0]  a, b;
    wire signed [31:0] out;

    integer errors = 0;

    mac dut (.clk(clk), .rst(rst), .a(a), .b(b), .out(out));

    initial clk = 0;
    always #5 clk = ~clk;

    task check;
        input signed [31:0] expected;
        input integer        label;
        begin
            if ($signed(out) !== expected) begin
                $display("FAIL step %0d: out=%0d expected=%0d", label, $signed(out), expected);
                errors = errors + 1;
            end else begin
                $display("PASS step %0d: out=%0d", label, $signed(out));
            end
        end
    endtask

    initial begin
        $dumpfile("mac_tb.vcd");
        $dumpvars(0, mac_tb);

        rst = 1; a = 0; b = 0;
        @(posedge clk); #1;
        check(0, 0);

        // a=3, b=4 for 3 cycles
        rst = 0; a = 3; b = 4;
        @(posedge clk); #1; check(12,  1);
        @(posedge clk); #1; check(24,  2);
        @(posedge clk); #1; check(36,  3);

        // assert rst
        rst = 1;
        @(posedge clk); #1; check(0, 4);

        // a=-5, b=2 for 2 cycles
        rst = 0; a = -5; b = 2;
        @(posedge clk); #1; check(-10, 5);
        @(posedge clk); #1; check(-20, 6);

        if (errors == 0)
            $display("ALL TESTS PASSED");
        else
            $display("%0d TEST(S) FAILED", errors);

        $finish;
    end
endmodule

codefest/cf04/hdl/mac_tb.vcd
$date
	Wed Apr 22 15:55:02 2026
$end
$version
	Icarus Verilog
$end
$timescale
	1ps
$end
$scope module mac_tb $end
$var wire 32 ! out [31:0] $end
$var reg 8 " a [7:0] $end
$var reg 8 # b [7:0] $end
$var reg 1 $ clk $end
$var reg 1 % rst $end
$var integer 32 & errors [31:0] $end
$scope module dut $end
$var wire 8 ' a [7:0] $end
$var wire 8 ( b [7:0] $end
$var wire 1 $ clk $end
$var wire 1 % rst $end
$var wire 16 ) product [15:0] $end
$var reg 32 * out [31:0] $end
$upscope $end
$scope task check $end
$var reg 32 + expected [31:0] $end
$var integer 32 , label [31:0] $end
$upscope $end
$upscope $end
$enddefinitions $end
$comment Show the parameter values. $end
$dumpall
$end
#0
$dumpvars
bx ,
bx +
bx *
b0 )
b0 (
b0 '
b0 &
1%
0$
b0 #
b0 "
bx !
$end
#5000
b0 !
b0 *
1$
#6000
b1100 )
b100 #
b100 (
b11 "
b11 '
0%
b0 ,
b0 +
#10000
0$
#15000
b1100 !
b1100 *
1$
#16000
b1 ,
b1100 +
#20000
0$
#25000
b11000 !
b11000 *
1$
#26000
b10 ,
b11000 +
#30000
0$
#35000
b100100 !
b100100 *
1$
#36000
1%
b11 ,
b100100 +
#40000
0$
#45000
b0 !
b0 *
1$
#46000
b10 #
b10 (
b1111111111110110 )
b11111011 "
b11111011 '
0%
b100 ,
b0 +
#50000
0$
#55000
b11111111111111111111111111110110 !
b11111111111111111111111111110110 *
1$
#56000
b101 ,
b11111111111111111111111111110110 +
#60000
0$
#65000
b11111111111111111111111111101100 !
b11111111111111111111111111101100 *
1$
#66000
b110 ,
b11111111111111111111111111101100 +
