project/m2/rtl/compute_core.sv
/*
 * compute_core.sv : Echo detection compute core
 *
 * Ports:
 *   clk        in    1         clock (single domain)
 *   rst        in    1         synchronous active-high reset
 *   valid_in   in    1         input sample pair is valid this cycle
 *   ref_in     in   DW         far-end reference sample (signed INT16)
 *   mic_in     in   DW         near-end mic sample (signed INT16)
 *   threshold  in   ACCW       echo threshold in accumulated cross-correlation units
 *   echo_det   out   1         1 = echo detected (acc_cross >= threshold)
 *   valid_out  out   1         output valid; goes high N+1 valid_in cycles after reset
 *
 * Computes Σref[i]*mic[i] over a sliding N-sample window and compares against threshold.
 * Full normalization (÷ sqrt(ref_energy * mic_energy)) is deferred to M3; see precision.md.
 * INT16 samples, 40-bit signed accumulators. Single clock domain, synchronous active-high reset.
 */
module compute_core #(
    parameter int N    = 128,
    parameter int DW   = 16,
    parameter int ACCW = 40    // DW*2 + ceil(log2(N)) + 1 = 32+7+1
) (
    input  logic                    clk,
    input  logic                    rst,
    input  logic                    valid_in,
    input  logic signed [DW-1:0]   ref_in,
    input  logic signed [DW-1:0]   mic_in,
    input  logic signed [ACCW-1:0] threshold,
    output logic                    echo_det,
    output logic                    valid_out
);

    localparam int CNTW = $clog2(N) + 1;  // 8 bits for N=128

    logic signed [DW-1:0]   ref_buf [0:N-1];
    logic signed [DW-1:0]   mic_buf [0:N-1];
    logic [CNTW-1:0]        win_cnt;

    // window_full goes high combinationally once win_cnt reaches N
    logic window_full;
    assign window_full = (win_cnt == CNTW'(N));

    // Sign-extend buffers to ACCW bits (combinational, synthesizes as wires)
    logic signed [ACCW-1:0] ref_e [0:N-1];
    logic signed [ACCW-1:0] mic_e [0:N-1];
    genvar g;
    generate
        for (g = 0; g < N; g++) begin : sign_ext
            assign ref_e[g] = ACCW'(ref_buf[g]);  // signed assignment sign-extends
            assign mic_e[g] = ACCW'(mic_buf[g]);
        end
    endgenerate

    // Parallel MAC tree: N multipliers evaluated combinationally each cycle
    logic signed [ACCW-1:0] acc_cross;

    always_comb begin : mac_tree
        acc_cross = '0;
        for (int i = 0; i < N; i++)
            acc_cross = acc_cross + ref_e[i] * mic_e[i];  // 40x40 -> 40-bit (lower bits)
    end

    always_ff @(posedge clk) begin
        if (rst) begin
            for (int i = 0; i < N; i++) begin
                ref_buf[i] <= '0;
                mic_buf[i] <= '0;
            end
            win_cnt   <= '0;
            echo_det  <= 1'b0;
            valid_out <= 1'b0;
        end else if (valid_in) begin
            // Shift new sample into buffer front
            ref_buf[0] <= ref_in;
            mic_buf[0] <= mic_in;
            for (int i = 1; i < N; i++) begin
                ref_buf[i] <= ref_buf[i-1];
                mic_buf[i] <= mic_buf[i-1];
            end
            if (!window_full)
                win_cnt <= win_cnt + 1'b1;
            // Register outputs; acc_cross is computed from pre-shift buffer
            echo_det  <= window_full & (acc_cross >= threshold);
            valid_out <= window_full;
        end else begin
            valid_out <= 1'b0;
        end
    end

endmodule

project/m2/rtl/interface.sv
/*
 * interface.sv  —  AXI4-Stream slave interface for echo detection chiplet
 *
 * Note: 'interface' is a SystemVerilog reserved keyword; module is named axi4s_rx.
 *   File named interface.sv per M2 spec. See project/m2/README.md.
 *
 * Ports:
 *   clk        in    1         clock (single domain)
 *   rst        in    1         synchronous active-high reset
 *   s_tvalid   in    1         AXI4-S: master data valid
 *   s_tready   out   1         AXI4-S: slave ready (always asserted; no back-pressure)
 *   s_tdata    in   32         AXI4-S: [31:16]=ref_sample, [15:0]=mic_sample
 *   ref_out    out  16         decoded far-end reference sample (signed INT16)
 *   mic_out    out  16         decoded near-end mic sample (signed INT16)
 *   valid_out  out   1         decoded pair valid (registered one cycle after TVALID)
 *
 * Protocol: AXI4-Stream (AMBA AXI4-S spec section 2).
 *   TREADY is wired high; transaction occurs on every TVALID cycle.
 *   TDATA packing: upper 16 bits = ref, lower 16 bits = mic.
 *   No TLAST, TKEEP, TSTRB (single-beat, continuous stream).
 * Clock domain: single. Reset: synchronous, active-high.
 */
module axi4s_rx (
    input  logic        clk,
    input  logic        rst,
    // AXI4-Stream slave
    input  logic        s_tvalid,
    output logic        s_tready,
    input  logic [31:0] s_tdata,
    // decoded outputs to compute_core
    output logic signed [15:0] ref_out,
    output logic signed [15:0] mic_out,
    output logic               valid_out
);

    // Always ready: accept every beat; no FIFO or flow control needed at 0.064 MB/s
    assign s_tready = 1'b1;

    always_ff @(posedge clk) begin
        if (rst) begin
            ref_out   <= '0;
            mic_out   <= '0;
            valid_out <= 1'b0;
        end else begin
            valid_out <= s_tvalid;
            if (s_tvalid) begin
                ref_out <= s_tdata[31:16];
                mic_out <= s_tdata[15:0];
            end
        end
    end

endmodule

project/m3/rtl/top.sv
/*
 * top.sv : Integrated top module — echo detection chiplet
 *
 * Ports:
 *   clk        in    1         clock (single domain)
 *   rst        in    1         synchronous active-high reset
 *   s_tvalid   in    1         AXI4-S: master data valid
 *   s_tready   out   1         AXI4-S: slave ready
 *   s_tdata    in   32         AXI4-S: [31:16]=ref_sample, [15:0]=mic_sample
 *   threshold  in   40         echo detection threshold (host-configured)
 *   echo_det   out   1         1 = echo detected
 *   valid_out  out   1         echo_det is valid
 *
 * Instantiates axi4s_rx (interface.sv) and compute_core.
 * No glue logic required: axi4s_rx.valid_out drives compute_core.valid_in directly.
 * Single clock domain, synchronous active-high reset.
 */
module top #(
    parameter int N    = 128,
    parameter int DW   = 16,
    parameter int ACCW = 40
) (
    input  logic                    clk,
    input  logic                    rst,
    input  logic                    s_tvalid,
    output logic                    s_tready,
    input  logic [31:0]             s_tdata,
    input  logic signed [ACCW-1:0] threshold,
    output logic                    echo_det,
    output logic                    valid_out
);

    logic signed [DW-1:0] ref_sample;
    logic signed [DW-1:0] mic_sample;
    logic                 sample_valid;

    axi4s_rx u_rx (
        .clk      (clk),
        .rst      (rst),
        .s_tvalid (s_tvalid),
        .s_tready (s_tready),
        .s_tdata  (s_tdata),
        .ref_out  (ref_sample),
        .mic_out  (mic_sample),
        .valid_out(sample_valid)
    );

    compute_core #(.N(N), .DW(DW), .ACCW(ACCW)) u_core (
        .clk      (clk),
        .rst      (rst),
        .valid_in (sample_valid),
        .ref_in   (ref_sample),
        .mic_in   (mic_sample),
        .threshold(threshold),
        .echo_det (echo_det),
        .valid_out(valid_out)
    );

endmodule

project/m3/tb/tb_top.sv
/*
 * tb_top.sv : End-to-end co-simulation testbench for integrated top module
 *
 * Drives the host-side AXI4-Stream interface (no direct compute_core access).
 * Two tests:
 *   Test 1: 128 beats with ref=1, mic=1 → acc_cross=128 >= threshold=64 → echo_det=1 (PASS)
 *   Test 2: 128 beats with ref=1, mic=-1 → acc_cross=-128 < threshold=64 → echo_det=0 (PASS)
 *
 * Independent reference: Python — sum(1*1 for _ in range(128))=128, sum(1*(-1) for _ in range(128))=-128
 *
 * Timing: axi4s_rx adds 1 cycle latency. compute_core needs N+1 valid_in pulses before valid_out.
 * Total: drive N beats → wait 2 more clock edges → sample outputs.
 */

`timescale 1ns/1ps

module tb_top;

    localparam int N    = 128;
    localparam int ACCW = 40;

    logic        clk, rst;
    logic        s_tvalid, s_tready;
    logic [31:0] s_tdata;
    logic signed [ACCW-1:0] threshold;
    logic        echo_det, valid_out;

    top #(.N(N)) dut (
        .clk      (clk),
        .rst      (rst),
        .s_tvalid (s_tvalid),
        .s_tready (s_tready),
        .s_tdata  (s_tdata),
        .threshold(threshold),
        .echo_det (echo_det),
        .valid_out(valid_out)
    );

    // 10 ns clock
    initial clk = 0;
    always #5 clk = ~clk;

    // VCD dump
    initial begin
        $dumpfile("project/m3/sim/cosim.vcd");
        $dumpvars(0, tb_top);
    end

    // Send n AXI-S beats then wait a few cycles for output to register.
    // compute_core needs N+1 valid_in pulses; interface adds 1 cycle latency,
    // so caller must pass n = N+1 to see the first valid echo_det output.
    task automatic send_beats(input logic [15:0] ref_val, mic_val, input int n);
        integer i;
        for (i = 0; i < n; i++) begin
            @(negedge clk);
            s_tvalid = 1'b1;
            s_tdata  = {ref_val, mic_val};
        end
        @(negedge clk);
        s_tvalid = 1'b0;
        s_tdata  = '0;
        repeat (4) @(posedge clk);
    endtask

    integer pass_count;
    initial begin
        pass_count = 0;
        rst       = 1'b1;
        s_tvalid  = 1'b0;
        s_tdata   = '0;
        threshold = 40'sd64;

        repeat (4) @(posedge clk);
        @(negedge clk);
        rst = 1'b0;

        // --- Test 1: ref=1, mic=1, expect echo_det=1 ---
        // Python ref: sum(1*1 for _ in range(128)) = 128 >= 64 → echo_det=1
        // N+1 beats: interface latency (1 cycle) + N valid_in needed to fill window + 1 to register output
        send_beats(16'sd1, 16'sd1, N + 1);
        if (echo_det === 1'b1) begin
            $display("Test 1 PASS: ref=1, mic=1, echo_det=%0b (expected 1)", echo_det);
            pass_count++;
        end else begin
            $display("Test 1 FAIL: ref=1, mic=1, echo_det=%0b (expected 1)", echo_det);
        end

        // Reset between tests
        @(negedge clk);
        rst = 1'b1;
        repeat (4) @(posedge clk);
        @(negedge clk);
        rst = 1'b0;

        // --- Test 2: ref=1, mic=-1, expect echo_det=0 ---
        // Python ref: sum(1*(-1) for _ in range(128)) = -128 < 64 → echo_det=0
        send_beats(16'sd1, 16'sd1 * (-1), N + 1);
        if (echo_det === 1'b0) begin
            $display("Test 2 PASS: ref=1, mic=-1, echo_det=%0b (expected 0)", echo_det);
            pass_count++;
        end else begin
            $display("Test 2 FAIL: ref=1, mic=-1, echo_det=%0b (expected 0)", echo_det);
        end

        if (pass_count == 2)
            $display("PASS: 2/2 tests passed");
        else
            $display("FAIL: %0d/2 tests passed", pass_count);

        #20;
        $finish;
    end

endmodule

project/m3/sim/cosim.vcd
$date
	Wed May 20 14:44:14 2026
$end
$version
	Icarus Verilog
$end
$timescale
	1ps
$end
$scope module tb_top $end
$var wire 1 ! s_tready $end
$var wire 1 " valid_out $end
$var wire 1 # echo_det $end
$var parameter 32 $ ACCW $end
$var parameter 32 % N $end
$var reg 1 & clk $end
$var reg 1 ' rst $end
$var reg 32 ( s_tdata [31:0] $end
$var reg 1 ) s_tvalid $end
$var reg 40 * threshold [39:0] $end
$var integer 32 + pass_count [31:0] $end
$scope module dut $end
$var wire 1 & clk $end
$var wire 1 ' rst $end
$var wire 32 , s_tdata [31:0] $end
$var wire 1 ! s_tready $end
$var wire 1 ) s_tvalid $end
$var wire 40 - threshold [39:0] $end
$var wire 1 " valid_out $end
$var wire 1 . sample_valid $end
$var wire 16 / ref_sample [15:0] $end
$var wire 16 0 mic_sample [15:0] $end
$var wire 1 # echo_det $end
$var parameter 32 1 ACCW $end
$var parameter 32 2 DW $end
$var parameter 32 3 N $end
$scope module u_core $end
$var wire 1 & clk $end
$var wire 1 ' rst $end
$var wire 40 4 threshold [39:0] $end
$var wire 1 5 window_full $end
$var wire 1 . valid_in $end
$var wire 16 6 ref_in [15:0] $end
$var wire 16 7 mic_in [15:0] $end
$var parameter 32 8 ACCW $end
$var parameter 32 9 CNTW $end
$var parameter 32 : DW $end
$var parameter 32 ; N $end
$var reg 40 < acc_cross [39:0] $end
$var reg 1 # echo_det $end
$var reg 1 " valid_out $end
$var reg 8 = win_cnt [7:0] $end
$scope begin sign_ext[0] $end
$var parameter 2 > g $end
$upscope $end
$scope begin sign_ext[1] $end
$var parameter 2 ? g $end
$upscope $end
$scope begin sign_ext[2] $end
$var parameter 3 @ g $end
$upscope $end
$scope begin sign_ext[3] $end
$var parameter 3 A g $end
$upscope $end
$scope begin sign_ext[4] $end
$var parameter 4 B g $end
$upscope $end
$scope begin sign_ext[5] $end
$var parameter 4 C g $end
$upscope $end
$scope begin sign_ext[6] $end
$var parameter 4 D g $end
$upscope $end
$scope begin sign_ext[7] $end
$var parameter 4 E g $end
$upscope $end
$scope begin sign_ext[8] $end
$var parameter 5 F g $end
$upscope $end
$scope begin sign_ext[9] $end
$var parameter 5 G g $end
$upscope $end
$scope begin sign_ext[10] $end
$var parameter 5 H g $end
$upscope $end
$scope begin sign_ext[11] $end
$var parameter 5 I g $end
$upscope $end
$scope begin sign_ext[12] $end
$var parameter 5 J g $end
$upscope $end
$scope begin sign_ext[13] $end
$var parameter 5 K g $end
$upscope $end
$scope begin sign_ext[14] $end
$var parameter 5 L g $end
$upscope $end
$scope begin sign_ext[15] $end
$var parameter 5 M g $end
$upscope $end
$scope begin sign_ext[16] $end
$var parameter 6 N g $end
$upscope $end
$scope begin sign_ext[17] $end
$var parameter 6 O g $end
$upscope $end
$scope begin sign_ext[18] $end
$var parameter 6 P g $end
$upscope $end
$scope begin sign_ext[19] $end
$var parameter 6 Q g $end
$upscope $end
$scope begin sign_ext[20] $end
$var parameter 6 R g $end
$upscope $end
$scope begin sign_ext[21] $end
$var parameter 6 S g $end
$upscope $end
$scope begin sign_ext[22] $end
$var parameter 6 T g $end
$upscope $end
$scope begin sign_ext[23] $end
$var parameter 6 U g $end
$upscope $end
$scope begin sign_ext[24] $end
$var parameter 6 V g $end
$upscope $end
$scope begin sign_ext[25] $end
$var parameter 6 W g $end
$upscope $end
$scope begin sign_ext[26] $end
$var parameter 6 X g $end
$upscope $end
$scope begin sign_ext[27] $end
$var parameter 6 Y g $end
$upscope $end
$scope begin sign_ext[28] $end
$var parameter 6 Z g $end
$upscope $end
$scope begin sign_ext[29] $end
$var parameter 6 [ g $end
$upscope $end
$scope begin sign_ext[30] $end
$var parameter 6 \ g $end
$upscope $end
$scope begin sign_ext[31] $end
$var parameter 6 ] g $end
$upscope $end
$scope begin sign_ext[32] $end
$var parameter 7 ^ g $end
$upscope $end
$scope begin sign_ext[33] $end
$var parameter 7 _ g $end
$upscope $end
$scope begin sign_ext[34] $end
$var parameter 7 ` g $end
$upscope $end
$scope begin sign_ext[35] $end
$var parameter 7 a g $end
$upscope $end
$scope begin sign_ext[36] $end
$var parameter 7 b g $end
$upscope $end
$scope begin sign_ext[37] $end
$var parameter 7 c g $end
$upscope $end
$scope begin sign_ext[38] $end
$var parameter 7 d g $end
$upscope $end
$scope begin sign_ext[39] $end
$var parameter 7 e g $end
$upscope $end
$scope begin sign_ext[40] $end
$var parameter 7 f g $end
$upscope $end
$scope begin sign_ext[41] $end
$var parameter 7 g g $end
$upscope $end
$scope begin sign_ext[42] $end
$var parameter 7 h g $end
$upscope $end
$scope begin sign_ext[43] $end
$var parameter 7 i g $end
$upscope $end
$scope begin sign_ext[44] $end
$var parameter 7 j g $end
$upscope $end
$scope begin sign_ext[45] $end
$var parameter 7 k g $end
$upscope $end
$scope begin sign_ext[46] $end
$var parameter 7 l g $end
$upscope $end
$scope begin sign_ext[47] $end
$var parameter 7 m g $end
$upscope $end
$scope begin sign_ext[48] $end
$var parameter 7 n g $end
$upscope $end
$scope begin sign_ext[49] $end
$var parameter 7 o g $end
$upscope $end
$scope begin sign_ext[50] $end
$var parameter 7 p g $end
$upscope $end
$scope begin sign_ext[51] $end
$var parameter 7 q g $end
$upscope $end
$scope begin sign_ext[52] $end
$var parameter 7 r g $end
$upscope $end
$scope begin sign_ext[53] $end
$var parameter 7 s g $end
$upscope $end
$scope begin sign_ext[54] $end
$var parameter 7 t g $end
$upscope $end
$scope begin sign_ext[55] $end
$var parameter 7 u g $end
$upscope $end
$scope begin sign_ext[56] $end
$var parameter 7 v g $end
$upscope $end
$scope begin sign_ext[57] $end
$var parameter 7 w g $end
$upscope $end
$scope begin sign_ext[58] $end
$var parameter 7 x g $end
$upscope $end
$scope begin sign_ext[59] $end
$var parameter 7 y g $end
$upscope $end
$scope begin sign_ext[60] $end
$var parameter 7 z g $end
$upscope $end
$scope begin sign_ext[61] $end
$var parameter 7 { g $end
$upscope $end
$scope begin sign_ext[62] $end
$var parameter 7 | g $end
$upscope $end
$scope begin sign_ext[63] $end
$var parameter 7 } g $end
$upscope $end
$scope begin sign_ext[64] $end
$var parameter 8 ~ g $end
$upscope $end
$scope begin sign_ext[65] $end
$var parameter 8 !" g $end
$upscope $end
$scope begin sign_ext[66] $end
$var parameter 8 "" g $end
$upscope $end
$scope begin sign_ext[67] $end
$var parameter 8 #" g $end
$upscope $end
$scope begin sign_ext[68] $end
$var parameter 8 $" g $end
$upscope $end
$scope begin sign_ext[69] $end
$var parameter 8 %" g $end
$upscope $end
$scope begin sign_ext[70] $end
$var parameter 8 &" g $end
$upscope $end
$scope begin sign_ext[71] $end
$var parameter 8 '" g $end
$upscope $end
$scope begin sign_ext[72] $end
$var parameter 8 (" g $end
$upscope $end
$scope begin sign_ext[73] $end
$var parameter 8 )" g $end
$upscope $end
$scope begin sign_ext[74] $end
$var parameter 8 *" g $end
$upscope $end
$scope begin sign_ext[75] $end
$var parameter 8 +" g $end
$upscope $end
$scope begin sign_ext[76] $end
$var parameter 8 ," g $end
$upscope $end
$scope begin sign_ext[77] $end
$var parameter 8 -" g $end
$upscope $end
$scope begin sign_ext[78] $end
$var parameter 8 ." g $end
$upscope $end
$scope begin sign_ext[79] $end
$var parameter 8 /" g $end
$upscope $end
$scope begin sign_ext[80] $end
$var parameter 8 0" g $end
$upscope $end
$scope begin sign_ext[81] $end
$var parameter 8 1" g $end
$upscope $end
$scope begin sign_ext[82] $end
$var parameter 8 2" g $end
$upscope $end
$scope begin sign_ext[83] $end
$var parameter 8 3" g $end
$upscope $end
$scope begin sign_ext[84] $end
$var parameter 8 4" g $end
$upscope $end
$scope begin sign_ext[85] $end
$var parameter 8 5" g $end
$upscope $end
$scope begin sign_ext[86] $end
$var parameter 8 6" g $end
$upscope $end
$scope begin sign_ext[87] $end
$var parameter 8 7" g $end
$upscope $end
$scope begin sign_ext[88] $end
$var parameter 8 8" g $end
$upscope $end
$scope begin sign_ext[89] $end
$var parameter 8 9" g $end
$upscope $end
$scope begin sign_ext[90] $end
$var parameter 8 :" g $end
$upscope $end
$scope begin sign_ext[91] $end
$var parameter 8 ;" g $end
$upscope $end
$scope begin sign_ext[92] $end
$var parameter 8 <" g $end
$upscope $end
$scope begin sign_ext[93] $end
$var parameter 8 =" g $end
$upscope $end
$scope begin sign_ext[94] $end
$var parameter 8 >" g $end
$upscope $end
$scope begin sign_ext[95] $end
$var parameter 8 ?" g $end
$upscope $end
$scope begin sign_ext[96] $end
$var parameter 8 @" g $end
$upscope $end
$scope begin sign_ext[97] $end
$var parameter 8 A" g $end
$upscope $end
$scope begin sign_ext[98] $end
$var parameter 8 B" g $end
$upscope $end
$scope begin sign_ext[99] $end
$var parameter 8 C" g $end
$upscope $end
$scope begin sign_ext[100] $end
$var parameter 8 D" g $end
$upscope $end
$scope begin sign_ext[101] $end
$var parameter 8 E" g $end
$upscope $end
$scope begin sign_ext[102] $end
$var parameter 8 F" g $end
$upscope $end
$scope begin sign_ext[103] $end
$var parameter 8 G" g $end
$upscope $end
$scope begin sign_ext[104] $end
$var parameter 8 H" g $end
$upscope $end
$scope begin sign_ext[105] $end
$var parameter 8 I" g $end
$upscope $end
$scope begin sign_ext[106] $end
$var parameter 8 J" g $end
$upscope $end
$scope begin sign_ext[107] $end
$var parameter 8 K" g $end
$upscope $end
$scope begin sign_ext[108] $end
$var parameter 8 L" g $end
$upscope $end
$scope begin sign_ext[109] $end
$var parameter 8 M" g $end
$upscope $end
$scope begin sign_ext[110] $end
$var parameter 8 N" g $end
$upscope $end
$scope begin sign_ext[111] $end
$var parameter 8 O" g $end
$upscope $end
$scope begin sign_ext[112] $end
$var parameter 8 P" g $end
$upscope $end
$scope begin sign_ext[113] $end
$var parameter 8 Q" g $end
$upscope $end
$scope begin sign_ext[114] $end
$var parameter 8 R" g $end
$upscope $end
$scope begin sign_ext[115] $end
$var parameter 8 S" g $end
$upscope $end
$scope begin sign_ext[116] $end
$var parameter 8 T" g $end
$upscope $end
$scope begin sign_ext[117] $end
$var parameter 8 U" g $end
$upscope $end
$scope begin sign_ext[118] $end
$var parameter 8 V" g $end
$upscope $end
$scope begin sign_ext[119] $end
$var parameter 8 W" g $end
$upscope $end
$scope begin sign_ext[120] $end
$var parameter 8 X" g $end
$upscope $end
$scope begin sign_ext[121] $end
$var parameter 8 Y" g $end
$upscope $end
$scope begin sign_ext[122] $end
$var parameter 8 Z" g $end
$upscope $end
$scope begin sign_ext[123] $end
$var parameter 8 [" g $end
$upscope $end
$scope begin sign_ext[124] $end
$var parameter 8 \" g $end
$upscope $end
$scope begin sign_ext[125] $end
$var parameter 8 ]" g $end
$upscope $end
$scope begin sign_ext[126] $end
$var parameter 8 ^" g $end
$upscope $end
$scope begin sign_ext[127] $end
$var parameter 8 _" g $end
$upscope $end
$scope begin $ivl_for_loop1 $end
$var integer 32 `" i [31:0] $end
$upscope $end
$scope begin $ivl_for_loop2 $end
$var integer 32 a" i [31:0] $end
$upscope $end
$scope begin mac_tree $end
$scope begin $ivl_for_loop0 $end
$var integer 32 b" i [31:0] $end
$upscope $end
$upscope $end
$upscope $end
$scope module u_rx $end
$var wire 1 & clk $end
$var wire 1 ' rst $end
$var wire 32 c" s_tdata [31:0] $end
$var wire 1 ! s_tready $end
$var wire 1 ) s_tvalid $end
$var reg 16 d" mic_out [15:0] $end
$var reg 16 e" ref_out [15:0] $end
$var reg 1 . valid_out $end
$upscope $end
$upscope $end
$scope task send_beats $end
$upscope $end
$upscope $end
$enddefinitions $end
$comment Show the parameter values. $end
$dumpall
b1111111 _"
b1111110 ^"
b1111101 ]"
b1111100 \"
b1111011 ["
b1111010 Z"
b1111001 Y"
b1111000 X"
b1110111 W"
b1110110 V"
b1110101 U"
b1110100 T"
b1110011 S"
b1110010 R"
b1110001 Q"
b1110000 P"
b1101111 O"
b1101110 N"
b1101101 M"
b1101100 L"
b1101011 K"
b1101010 J"
b1101001 I"
b1101000 H"
b1100111 G"
b1100110 F"
b1100101 E"
b1100100 D"
b1100011 C"
b1100010 B"
b1100001 A"
b1100000 @"
b1011111 ?"
b1011110 >"
b1011101 ="
b1011100 <"
b1011011 ;"
b1011010 :"
b1011001 9"
b1011000 8"
b1010111 7"
b1010110 6"
b1010101 5"
b1010100 4"
b1010011 3"
b1010010 2"
b1010001 1"
b1010000 0"
b1001111 /"
b1001110 ."
b1001101 -"
b1001100 ,"
b1001011 +"
b1001010 *"
b1001001 )"
b1001000 ("
b1000111 '"
b1000110 &"
b1000101 %"
b1000100 $"
b1000011 #"
b1000010 ""
b1000001 !"
b1000000 ~
b111111 }
b111110 |
b111101 {
b111100 z
b111011 y
b111010 x
b111001 w
b111000 v
b110111 u
b110110 t
b110101 s
b110100 r
b110011 q
b110010 p
b110001 o
b110000 n
b101111 m
b101110 l
b101101 k
b101100 j
b101011 i
b101010 h
b101001 g
b101000 f
b100111 e
b100110 d
b100101 c
b100100 b
b100011 a
b100010 `
b100001 _
b100000 ^
b11111 ]
b11110 \
b11101 [
b11100 Z
b11011 Y
b11010 X
b11001 W
b11000 V
b10111 U
b10110 T
b10101 S
b10100 R
b10011 Q
b10010 P
b10001 O
b10000 N
b1111 M
b1110 L
b1101 K
b1100 J
b1011 I
b1010 H
b1001 G
b1000 F
b111 E
b110 D
b101 C
b100 B
b11 A
b10 @
b1 ?
b0 >
b10000000 ;
b10000 :
b1000 9
b101000 8
b10000000 3
b10000 2
b101000 1
b10000000 %
b101000 $
$end
#0
$dumpvars
bx e"
bx d"
b0 c"
b10000000 b"
b0 a"
b0 `"
bx =
bx <
bx 7
bx 6
x5
b1000000 4
bx 0
bx /
x.
b1000000 -
b0 ,
b0 +
b1000000 *
0)
b0 (
1'
0&
x#
x"
1!
$end
#5000
b10000000 b"
b0 <
0"
0#
05
b0 =
0.
b0 0
b0 7
b0 d"
b0 /
b0 6
b0 e"
b10000000 `"
1&
#10000
0&
#15000
b10000000 `"
1&
#20000
0&
#25000
b10000000 `"
1&
#30000
0&
#35000
b10000000 `"
1&
#40000
0'
0&
#45000
1&
#50000
b10000000000000001 (
b10000000000000001 ,
b10000000000000001 c"
1)
0&
#55000
b1 0
b1 7
b1 d"
b1 /
b1 6
b1 e"
1.
1&
#60000
0&
#65000
b1 <
b10000000 b"
b1 =
b10000000 a"
1&
#70000
0&
#75000
b10000000 b"
b10 <
b10 =
b10000000 a"
1&
#80000
0&
#85000
b10000000 b"
b11 <
b11 =
b10000000 a"
1&
#90000
0&
#95000
b10000000 b"
b100 <
b100 =
b10000000 a"
1&
#100000
0&
#105000
b10000000 b"
b101 <
b101 =
b10000000 a"
1&
#110000
0&
#115000
b10000000 b"
b110 <
b110 =
b10000000 a"
1&
#120000
0&
#125000
b10000000 b"
b111 <
b111 =
b10000000 a"
1&
#130000
0&
#135000
b10000000 b"
b1000 <
b1000 =
b10000000 a"
1&
#140000
0&
#145000
b10000000 b"
b1001 <
b1001 =
b10000000 a"
1&
#150000
0&
#155000
b10000000 b"
b1010 <
b1010 =
b10000000 a"
1&
#160000
0&
#165000
b10000000 b"
b1011 <
b1011 =
b10000000 a"
1&
#170000
0&
#175000
b10000000 b"
b1100 <
b1100 =
b10000000 a"
1&
#180000
0&
#185000
b10000000 b"
b1101 <
b1101 =
b10000000 a"
1&
#190000
0&
#195000
b10000000 b"
b1110 <
b1110 =
b10000000 a"
1&
#200000
0&
#205000
b10000000 b"
b1111 <
b1111 =
b10000000 a"
1&
#210000
0&
#215000
b10000000 b"
b10000 <
b10000 =
b10000000 a"
1&
#220000
0&
#225000
b10000000 b"
b10001 <
b10001 =
b10000000 a"
1&
#230000
0&
#235000
b10000000 b"
b10010 <
b10010 =
b10000000 a"
1&
#240000
0&
#245000
b10000000 b"
b10011 <
b10011 =
b10000000 a"
1&
#250000
0&
#255000
b10000000 b"
b10100 <
b10100 =
b10000000 a"
1&
#260000
0&
#265000
b10000000 b"
b10101 <
b10101 =
b10000000 a"
1&
#270000
0&
#275000
b10000000 b"
b10110 <
b10110 =
b10000000 a"
1&
#280000
0&
#285000
b10000000 b"
b10111 <
b10111 =
b10000000 a"
1&
#290000
0&
#295000
b10000000 b"
b11000 <
b11000 =
b10000000 a"
1&
#300000
0&
#305000
b10000000 b"
b11001 <
b11001 =
b10000000 a"
1&
#310000
0&
#315000
b10000000 b"
b11010 <
b11010 =
b10000000 a"
1&
#320000
0&
#325000
b10000000 b"
b11011 <
b11011 =
b10000000 a"
1&
#330000
0&
#335000
b10000000 b"
b11100 <
b11100 =
b10000000 a"
1&
#340000
0&
#345000
b10000000 b"
b11101 <
b11101 =
b10000000 a"
1&
#350000
0&
#355000
b10000000 b"
b11110 <
b11110 =
b10000000 a"
1&
#360000
0&
#365000
b10000000 b"
b11111 <
b11111 =
b10000000 a"
1&
#370000
0&
#375000
b10000000 b"
b100000 <
b100000 =
b10000000 a"
1&
#380000
0&
#385000
b10000000 b"
b100001 <
b100001 =
b10000000 a"
1&
#390000
0&
#395000
b10000000 b"
b100010 <
b100010 =
b10000000 a"
1&
#400000
0&
#405000
b10000000 b"
b100011 <
b100011 =
b10000000 a"
1&
#410000
0&
#415000
b10000000 b"
b100100 <
b100100 =
b10000000 a"
1&
#420000
0&
#425000
b10000000 b"
b100101 <
b100101 =
b10000000 a"
1&
#430000
0&
#435000
b10000000 b"
b100110 <
b100110 =
b10000000 a"
1&
#440000
0&
#445000
b10000000 b"
b100111 <
b100111 =
b10000000 a"
1&
#450000
0&
#455000
b10000000 b"
b101000 <
b101000 =
b10000000 a"
1&
#460000
0&
#465000
b10000000 b"
b101001 <
b101001 =
b10000000 a"
1&
#470000
0&
#475000
b10000000 b"
b101010 <
b101010 =
b10000000 a"
1&
#480000
0&
#485000
b10000000 b"
b101011 <
b101011 =
b10000000 a"
1&
#490000
0&
#495000
b10000000 b"
b101100 <
b101100 =
b10000000 a"
1&
#500000
0&
#505000
b10000000 b"
b101101 <
b101101 =
b10000000 a"
1&
#510000
0&
#515000
b10000000 b"
b101110 <
b101110 =
b10000000 a"
1&
#520000
0&
#525000
b10000000 b"
b101111 <
b101111 =
b10000000 a"
1&
#530000
0&
#535000
b10000000 b"
b110000 <
b110000 =
b10000000 a"
1&
#540000
0&
#545000
b10000000 b"
b110001 <
b110001 =
b10000000 a"
1&
#550000
0&
#555000
b10000000 b"
b110010 <
b110010 =
b10000000 a"
1&
#560000
0&
#565000
b10000000 b"
b110011 <
b110011 =
b10000000 a"
1&
#570000
0&
#575000
b10000000 b"
b110100 <
b110100 =
b10000000 a"
1&
#580000
0&
#585000
b10000000 b"
b110101 <
b110101 =
b10000000 a"
1&
#590000
0&
#595000
b10000000 b"
b110110 <
b110110 =
b10000000 a"
1&
#600000
0&
#605000
b10000000 b"
b110111 <
b110111 =
b10000000 a"
1&
#610000
0&
#615000
b10000000 b"
b111000 <
b111000 =
b10000000 a"
1&
#620000
0&
#625000
b10000000 b"
b111001 <
b111001 =
b10000000 a"
1&
#630000
0&
#635000
b10000000 b"
b111010 <
b111010 =
b10000000 a"
1&
#640000
0&
#645000
b10000000 b"
b111011 <
b111011 =
b10000000 a"
1&
#650000
0&
#655000
b10000000 b"
b111100 <
b111100 =
b10000000 a"
1&
#660000
0&
#665000
b10000000 b"
b111101 <
b111101 =
b10000000 a"
1&
#670000
0&
#675000
b10000000 b"
b111110 <
b111110 =
b10000000 a"
1&
#680000
0&
#685000
b10000000 b"
b111111 <
b111111 =
b10000000 a"
1&
#690000
0&
#695000
b10000000 b"
b1000000 <
b1000000 =
b10000000 a"
1&
#700000
0&
#705000
b10000000 b"
b1000001 <
b1000001 =
b10000000 a"
1&
#710000
0&
#715000
b10000000 b"
b1000010 <
b1000010 =
b10000000 a"
1&
#720000
0&
#725000
b10000000 b"
b1000011 <
b1000011 =
b10000000 a"
1&
#730000
0&
#735000
b10000000 b"
b1000100 <
b1000100 =
b10000000 a"
1&
#740000
0&
#745000
b10000000 b"
b1000101 <
b1000101 =
b10000000 a"
1&
#750000
0&
#755000
b10000000 b"
b1000110 <
b1000110 =
b10000000 a"
1&
#760000
0&
#765000
b10000000 b"
b1000111 <
b1000111 =
b10000000 a"
1&
